{
  "gui": {
    "version": "v0.18.4.4",
    "downloads": [
      {
        "href": "https://downloads.getmonero.org/gui/win64install",
        "label": "Windows (Installer)",
        "platform": "windows",
        "size": "95.19 MB"
      },
      {
        "href": "https://downloads.getmonero.org/gui/win64",
        "label": "Windows (.zip)",
        "platform": "windows",
        "size": "132.46 MB"
      },
      "separator",
      {
        "href": "https://downloads.getmonero.org/gui/mac64",
        "label": "macOS (Intel)",
        "platform": "macos",
        "size": "65.36 MB"
      },
      {
        "href": "https://downloads.getmonero.org/gui/macarm8",
        "label": "macOS (Apple Silicon)",
        "platform": "macos",
        "size": "47.04 MB"
      },
      "separator",
      {
        "href": "https://downloads.getmonero.org/gui/linux64",
        "label": "Linux (Tarball)",
        "platform": "linux",
        "size": "125.59 MB"
      }
    ],
    "torrent": "https://downloads.getmonero.org/gui/monero-gui-v0.18.4.4.torrent",
    "magnet": "magnet:?xt=urn:btih:1234567890abcdef&dn=monero-gui-v0.18.4.4&tr=udp%3A%2F%2Ftracker.opentrackr.org%3A1337%2Fannounce",
    "name": "Fluorine Fermi"
  },
  "cli": {
    "version": "v0.18.4.4",
    "downloads": [
      {
        "href": "https://downloads.getmonero.org/cli/win64",
        "label": "Windows (64-bit)",
        "platform": "windows",
        "size": "84.24 MB"
      },
      {
        "href": "https://downloads.getmonero.org/cli/win32",
        "label": "Windows (32-bit)",
        "platform": "windows",
        "size": "80.73 MB"
      },
      "separator",
      {
        "href": "https://downloads.getmonero.org/cli/mac64",
        "label": "macOS (Intel)",
        "platform": "macos",
        "size": "75.86 MB"
      },
      {
        "href": "https://downloads.getmonero.org/cli/macarm8",
        "label": "macOS (Apple Silicon)",
        "platform": "macos",
        "size": "66.13 MB"
      },
      "separator",
      {
        "href": "https://downloads.getmonero.org/cli/linux64",
        "label": "Linux (64-bit)",
        "platform": "linux",
        "size": "79.72 MB"
      },
      {
        "href": "https://downloads.getmonero.org/cli/linux32",
        "label": "Linux (32-bit)",
        "platform": "linux",
        "size": "80.90 MB"
      },
      {
        "href": "https://downloads.getmonero.org/cli/linuxarm8",
        "label": "Linux (ARMv8)",
        "platform": "linux",
        "size": "70.07 MB"
      },
      {
        "href": "https://downloads.getmonero.org/cli/linuxarm7",
        "label": "Linux (ARMv7)",
        "platform": "linux",
        "size": "68.79 MB"
      },
      {
        "href": "https://downloads.getmonero.org/cli/linuxriscv64",
        "label": "Linux (RISC-V 64-bit)",
        "platform": "linux",
        "size": "74.21 MB"
      },
      "separator",
      {
        "href": "https://downloads.getmonero.org/cli/androidarm8",
        "label": "Android (ARMv8)",
        "platform": "android",
        "size": "85.54 MB"
      },
      {
        "href": "https://downloads.getmonero.org/cli/androidarm7",
        "label": "Android (ARMv7)",
        "platform": "android",
        "size": "87.69 MB"
      },
      "separator",
      {
        "href": "https://downloads.getmonero.org/cli/freebsd64",
        "label": "FreeBSD (64-bit)",
        "platform": "freebsd",
        "size": "71.24 MB"
      }
    ],
    "torrent": "https://downloads.getmonero.org/cli/monero-cli-v0.18.4.4.torrent",
    "magnet": "magnet:?xt=urn:btih:fedcba0987654321&dn=monero-cli-v0.18.4.4&tr=udp%3A%2F%2Ftracker.opentrackr.org%3A1337%2Fannounce",
    "name": "Fluorine Fermi"
  }
}
